wuddz_m3u/m3u.py
wuddz_m3u-1.0.3.dist-info/METADATA
wuddz_m3u-1.0.3.dist-info/WHEEL
wuddz_m3u-1.0.3.dist-info/entry_points.txt
wuddz_m3u-1.0.3.dist-info/licenses/LICENSE
wuddz_m3u-1.0.3.dist-info/RECORD
