Metadata-Version: 2.3
Name: wuddz_m3u
Version: 1.0.3
Summary: A Cool & Simple Python M3U Playlist Checker/Downloader/Maker/Parser & XPSF To M3U Converter.
Project-URL: Homepage, https://github.com/wuddz-devs/wuddz-m3u
Author-email: Wuddz-Devs <wuddz_devs@protonmail.com>
License: MIT License
Keywords: m3u,media,music,playlist,re,regex,video,xspf
Classifier: License :: OSI Approved :: MIT License
Classifier: Programming Language :: Python
Classifier: Programming Language :: Python :: 3.7
Classifier: Programming Language :: Python :: 3.8
Classifier: Programming Language :: Python :: 3.9
Classifier: Programming Language :: Python :: 3.10
Requires-Python: >=3.7
Requires-Dist: colorama
Requires-Dist: requests
